{
  "id": "f0acc760-0326-4f3f-8939-35d75362624b",
  "prevId": "8c51c5e2-cdc6-438f-82f7-cb0b1b0a5d8e",
  "version": "7",
  "dialect": "postgresql",
  "tables": {
    "public.account": {
      "name": "account",
      "schema": "",
      "columns": {
        "id": {
          "name": "id",
          "type": "text",
          "primaryKey": true,
          "notNull": true
        },
        "account_id": {
          "name": "account_id",
          "type": "text",
          "primaryKey": false,
          "notNull": true
        },
        "provider_id": {
          "name": "provider_id",
          "type": "text",
          "primaryKey": false,
          "notNull": true
        },
        "user_id": {
          "name": "user_id",
          "type": "text",
          "primaryKey": false,
          "notNull": true
        },
        "access_token": {
          "name": "access_token",
          "type": "text",
          "primaryKey": false,
          "notNull": false
        },
        "refresh_token": {
          "name": "refresh_token",
          "type": "text",
          "primaryKey": false,
          "notNull": false
        },
        "id_token": {
          "name": "id_token",
          "type": "text",
          "primaryKey": false,
          "notNull": false
        },
        "access_token_expires_at": {
          "name": "access_token_expires_at",
          "type": "timestamp",
          "primaryKey": false,
          "notNull": false
        },
        "refresh_token_expires_at": {
          "name": "refresh_token_expires_at",
          "type": "timestamp",
          "primaryKey": false,
          "notNull": false
        },
        "scope": {
          "name": "scope",
          "type": "text",
          "primaryKey": false,
          "notNull": false
        },
        "password": {
          "name": "password",
          "type": "text",
          "primaryKey": false,
          "notNull": false
        },
        "created_at": {
          "name": "created_at",
          "type": "timestamp",
          "primaryKey": false,
          "notNull": true,
          "default": "now()"
        },
        "updated_at": {
          "name": "updated_at",
          "type": "timestamp",
          "primaryKey": false,
          "notNull": true
        }
      },
      "indexes": {
        "account_userId_idx": {
          "name": "account_userId_idx",
          "columns": [
            {
              "expression": "user_id",
              "isExpression": false,
              "asc": true,
              "nulls": "last"
            }
          ],
          "isUnique": false,
          "concurrently": false,
          "method": "btree",
          "with": {}
        }
      },
      "foreignKeys": {
        "account_user_id_user_id_fk": {
          "name": "account_user_id_user_id_fk",
          "tableFrom": "account",
          "tableTo": "user",
          "columnsFrom": [
            "user_id"
          ],
          "columnsTo": [
            "id"
          ],
          "onDelete": "cascade",
          "onUpdate": "no action"
        }
      },
      "compositePrimaryKeys": {},
      "uniqueConstraints": {},
      "policies": {},
      "checkConstraints": {},
      "isRLSEnabled": false
    },
    "public.passkey": {
      "name": "passkey",
      "schema": "",
      "columns": {
        "id": {
          "name": "id",
          "type": "text",
          "primaryKey": true,
          "notNull": true
        },
        "name": {
          "name": "name",
          "type": "text",
          "primaryKey": false,
          "notNull": false
        },
        "public_key": {
          "name": "public_key",
          "type": "text",
          "primaryKey": false,
          "notNull": true
        },
        "user_id": {
          "name": "user_id",
          "type": "text",
          "primaryKey": false,
          "notNull": true
        },
        "credential_id": {
          "name": "credential_id",
          "type": "text",
          "primaryKey": false,
          "notNull": true
        },
        "counter": {
          "name": "counter",
          "type": "integer",
          "primaryKey": false,
          "notNull": true
        },
        "device_type": {
          "name": "device_type",
          "type": "text",
          "primaryKey": false,
          "notNull": true
        },
        "backed_up": {
          "name": "backed_up",
          "type": "boolean",
          "primaryKey": false,
          "notNull": true
        },
        "transports": {
          "name": "transports",
          "type": "text",
          "primaryKey": false,
          "notNull": false
        },
        "created_at": {
          "name": "created_at",
          "type": "timestamp",
          "primaryKey": false,
          "notNull": false
        },
        "aaguid": {
          "name": "aaguid",
          "type": "text",
          "primaryKey": false,
          "notNull": false
        }
      },
      "indexes": {
        "passkey_userId_idx": {
          "name": "passkey_userId_idx",
          "columns": [
            {
              "expression": "user_id",
              "isExpression": false,
              "asc": true,
              "nulls": "last"
            }
          ],
          "isUnique": false,
          "concurrently": false,
          "method": "btree",
          "with": {}
        },
        "passkey_credentialID_idx": {
          "name": "passkey_credentialID_idx",
          "columns": [
            {
              "expression": "credential_id",
              "isExpression": false,
              "asc": true,
              "nulls": "last"
            }
          ],
          "isUnique": false,
          "concurrently": false,
          "method": "btree",
          "with": {}
        }
      },
      "foreignKeys": {
        "passkey_user_id_user_id_fk": {
          "name": "passkey_user_id_user_id_fk",
          "tableFrom": "passkey",
          "tableTo": "user",
          "columnsFrom": [
            "user_id"
          ],
          "columnsTo": [
            "id"
          ],
          "onDelete": "cascade",
          "onUpdate": "no action"
        }
      },
      "compositePrimaryKeys": {},
      "uniqueConstraints": {},
      "policies": {},
      "checkConstraints": {},
      "isRLSEnabled": false
    },
    "public.session": {
      "name": "session",
      "schema": "",
      "columns": {
        "id": {
          "name": "id",
          "type": "text",
          "primaryKey": true,
          "notNull": true
        },
        "expires_at": {
          "name": "expires_at",
          "type": "timestamp",
          "primaryKey": false,
          "notNull": true
        },
        "token": {
          "name": "token",
          "type": "text",
          "primaryKey": false,
          "notNull": true
        },
        "created_at": {
          "name": "created_at",
          "type": "timestamp",
          "primaryKey": false,
          "notNull": true,
          "default": "now()"
        },
        "updated_at": {
          "name": "updated_at",
          "type": "timestamp",
          "primaryKey": false,
          "notNull": true
        },
        "ip_address": {
          "name": "ip_address",
          "type": "text",
          "primaryKey": false,
          "notNull": false
        },
        "user_agent": {
          "name": "user_agent",
          "type": "text",
          "primaryKey": false,
          "notNull": false
        },
        "user_id": {
          "name": "user_id",
          "type": "text",
          "primaryKey": false,
          "notNull": true
        }
      },
      "indexes": {
        "session_userId_idx": {
          "name": "session_userId_idx",
          "columns": [
            {
              "expression": "user_id",
              "isExpression": false,
              "asc": true,
              "nulls": "last"
            }
          ],
          "isUnique": false,
          "concurrently": false,
          "method": "btree",
          "with": {}
        }
      },
      "foreignKeys": {
        "session_user_id_user_id_fk": {
          "name": "session_user_id_user_id_fk",
          "tableFrom": "session",
          "tableTo": "user",
          "columnsFrom": [
            "user_id"
          ],
          "columnsTo": [
            "id"
          ],
          "onDelete": "cascade",
          "onUpdate": "no action"
        }
      },
      "compositePrimaryKeys": {},
      "uniqueConstraints": {
        "session_token_unique": {
          "name": "session_token_unique",
          "nullsNotDistinct": false,
          "columns": [
            "token"
          ]
        }
      },
      "policies": {},
      "checkConstraints": {},
      "isRLSEnabled": false
    },
    "public.user": {
      "name": "user",
      "schema": "",
      "columns": {
        "id": {
          "name": "id",
          "type": "text",
          "primaryKey": true,
          "notNull": true
        },
        "name": {
          "name": "name",
          "type": "text",
          "primaryKey": false,
          "notNull": true
        },
        "email": {
          "name": "email",
          "type": "text",
          "primaryKey": false,
          "notNull": true
        },
        "email_verified": {
          "name": "email_verified",
          "type": "boolean",
          "primaryKey": false,
          "notNull": true,
          "default": false
        },
        "image": {
          "name": "image",
          "type": "text",
          "primaryKey": false,
          "notNull": false
        },
        "created_at": {
          "name": "created_at",
          "type": "timestamp",
          "primaryKey": false,
          "notNull": true,
          "default": "now()"
        },
        "updated_at": {
          "name": "updated_at",
          "type": "timestamp",
          "primaryKey": false,
          "notNull": true,
          "default": "now()"
        }
      },
      "indexes": {},
      "foreignKeys": {},
      "compositePrimaryKeys": {},
      "uniqueConstraints": {
        "user_email_unique": {
          "name": "user_email_unique",
          "nullsNotDistinct": false,
          "columns": [
            "email"
          ]
        }
      },
      "policies": {},
      "checkConstraints": {},
      "isRLSEnabled": false
    },
    "public.verification": {
      "name": "verification",
      "schema": "",
      "columns": {
        "id": {
          "name": "id",
          "type": "text",
          "primaryKey": true,
          "notNull": true
        },
        "identifier": {
          "name": "identifier",
          "type": "text",
          "primaryKey": false,
          "notNull": true
        },
        "value": {
          "name": "value",
          "type": "text",
          "primaryKey": false,
          "notNull": true
        },
        "expires_at": {
          "name": "expires_at",
          "type": "timestamp",
          "primaryKey": false,
          "notNull": true
        },
        "created_at": {
          "name": "created_at",
          "type": "timestamp",
          "primaryKey": false,
          "notNull": true,
          "default": "now()"
        },
        "updated_at": {
          "name": "updated_at",
          "type": "timestamp",
          "primaryKey": false,
          "notNull": true,
          "default": "now()"
        }
      },
      "indexes": {
        "verification_identifier_idx": {
          "name": "verification_identifier_idx",
          "columns": [
            {
              "expression": "identifier",
              "isExpression": false,
              "asc": true,
              "nulls": "last"
            }
          ],
          "isUnique": false,
          "concurrently": false,
          "method": "btree",
          "with": {}
        }
      },
      "foreignKeys": {},
      "compositePrimaryKeys": {},
      "uniqueConstraints": {},
      "policies": {},
      "checkConstraints": {},
      "isRLSEnabled": false
    },
    "public.api_key": {
      "name": "api_key",
      "schema": "",
      "columns": {
        "id": {
          "name": "id",
          "type": "text",
          "primaryKey": true,
          "notNull": true
        },
        "config_id": {
          "name": "config_id",
          "type": "text",
          "primaryKey": false,
          "notNull": true,
          "default": "'default'"
        },
        "name": {
          "name": "name",
          "type": "text",
          "primaryKey": false,
          "notNull": false
        },
        "start": {
          "name": "start",
          "type": "text",
          "primaryKey": false,
          "notNull": false
        },
        "prefix": {
          "name": "prefix",
          "type": "text",
          "primaryKey": false,
          "notNull": false
        },
        "key": {
          "name": "key",
          "type": "text",
          "primaryKey": false,
          "notNull": true
        },
        "reference_id": {
          "name": "reference_id",
          "type": "text",
          "primaryKey": false,
          "notNull": true
        },
        "refill_interval": {
          "name": "refill_interval",
          "type": "bigint",
          "primaryKey": false,
          "notNull": false
        },
        "refill_amount": {
          "name": "refill_amount",
          "type": "integer",
          "primaryKey": false,
          "notNull": false
        },
        "last_refill_at": {
          "name": "last_refill_at",
          "type": "timestamp",
          "primaryKey": false,
          "notNull": false
        },
        "enabled": {
          "name": "enabled",
          "type": "boolean",
          "primaryKey": false,
          "notNull": false,
          "default": true
        },
        "rate_limit_enabled": {
          "name": "rate_limit_enabled",
          "type": "boolean",
          "primaryKey": false,
          "notNull": false,
          "default": true
        },
        "rate_limit_time_window": {
          "name": "rate_limit_time_window",
          "type": "bigint",
          "primaryKey": false,
          "notNull": false
        },
        "rate_limit_max": {
          "name": "rate_limit_max",
          "type": "integer",
          "primaryKey": false,
          "notNull": false
        },
        "request_count": {
          "name": "request_count",
          "type": "integer",
          "primaryKey": false,
          "notNull": false
        },
        "remaining": {
          "name": "remaining",
          "type": "integer",
          "primaryKey": false,
          "notNull": false
        },
        "last_request": {
          "name": "last_request",
          "type": "timestamp",
          "primaryKey": false,
          "notNull": false
        },
        "expires_at": {
          "name": "expires_at",
          "type": "timestamp",
          "primaryKey": false,
          "notNull": false
        },
        "created_at": {
          "name": "created_at",
          "type": "timestamp",
          "primaryKey": false,
          "notNull": true,
          "default": "now()"
        },
        "updated_at": {
          "name": "updated_at",
          "type": "timestamp",
          "primaryKey": false,
          "notNull": true,
          "default": "now()"
        },
        "metadata": {
          "name": "metadata",
          "type": "text",
          "primaryKey": false,
          "notNull": false
        },
        "permissions": {
          "name": "permissions",
          "type": "text",
          "primaryKey": false,
          "notNull": false
        }
      },
      "indexes": {
        "api_key_config_id_idx": {
          "name": "api_key_config_id_idx",
          "columns": [
            {
              "expression": "config_id",
              "isExpression": false,
              "asc": true,
              "nulls": "last"
            }
          ],
          "isUnique": false,
          "concurrently": false,
          "method": "btree",
          "with": {}
        },
        "api_key_key_idx": {
          "name": "api_key_key_idx",
          "columns": [
            {
              "expression": "key",
              "isExpression": false,
              "asc": true,
              "nulls": "last"
            }
          ],
          "isUnique": false,
          "concurrently": false,
          "method": "btree",
          "with": {}
        },
        "api_key_reference_id_idx": {
          "name": "api_key_reference_id_idx",
          "columns": [
            {
              "expression": "reference_id",
              "isExpression": false,
              "asc": true,
              "nulls": "last"
            }
          ],
          "isUnique": false,
          "concurrently": false,
          "method": "btree",
          "with": {}
        }
      },
      "foreignKeys": {},
      "compositePrimaryKeys": {},
      "uniqueConstraints": {},
      "policies": {},
      "checkConstraints": {},
      "isRLSEnabled": false
    },
    "public.rate_limit": {
      "name": "rate_limit",
      "schema": "",
      "columns": {
        "id": {
          "name": "id",
          "type": "text",
          "primaryKey": true,
          "notNull": true
        },
        "key": {
          "name": "key",
          "type": "text",
          "primaryKey": false,
          "notNull": true
        },
        "count": {
          "name": "count",
          "type": "integer",
          "primaryKey": false,
          "notNull": true
        },
        "last_request": {
          "name": "last_request",
          "type": "bigint",
          "primaryKey": false,
          "notNull": true
        }
      },
      "indexes": {},
      "foreignKeys": {},
      "compositePrimaryKeys": {},
      "uniqueConstraints": {
        "rate_limit_key_unique": {
          "name": "rate_limit_key_unique",
          "nullsNotDistinct": false,
          "columns": [
            "key"
          ]
        }
      },
      "policies": {},
      "checkConstraints": {},
      "isRLSEnabled": false
    },
    "public.groups": {
      "name": "groups",
      "schema": "",
      "columns": {
        "id": {
          "name": "id",
          "type": "text",
          "primaryKey": true,
          "notNull": true
        },
        "name": {
          "name": "name",
          "type": "text",
          "primaryKey": false,
          "notNull": true
        },
        "settlement_currency": {
          "name": "settlement_currency",
          "type": "text",
          "primaryKey": false,
          "notNull": true
        },
        "created_by": {
          "name": "created_by",
          "type": "text",
          "primaryKey": false,
          "notNull": true
        },
        "created_at": {
          "name": "created_at",
          "type": "timestamp",
          "primaryKey": false,
          "notNull": true,
          "default": "now()"
        },
        "deleted_at": {
          "name": "deleted_at",
          "type": "timestamp",
          "primaryKey": false,
          "notNull": false
        }
      },
      "indexes": {},
      "foreignKeys": {
        "groups_created_by_user_id_fk": {
          "name": "groups_created_by_user_id_fk",
          "tableFrom": "groups",
          "tableTo": "user",
          "columnsFrom": [
            "created_by"
          ],
          "columnsTo": [
            "id"
          ],
          "onDelete": "no action",
          "onUpdate": "no action"
        }
      },
      "compositePrimaryKeys": {},
      "uniqueConstraints": {},
      "policies": {},
      "checkConstraints": {},
      "isRLSEnabled": false
    },
    "public.invites": {
      "name": "invites",
      "schema": "",
      "columns": {
        "id": {
          "name": "id",
          "type": "text",
          "primaryKey": true,
          "notNull": true
        },
        "group_id": {
          "name": "group_id",
          "type": "text",
          "primaryKey": false,
          "notNull": true
        },
        "token": {
          "name": "token",
          "type": "text",
          "primaryKey": false,
          "notNull": true
        },
        "expires_at": {
          "name": "expires_at",
          "type": "timestamp",
          "primaryKey": false,
          "notNull": true
        },
        "revoked_at": {
          "name": "revoked_at",
          "type": "timestamp",
          "primaryKey": false,
          "notNull": false
        },
        "created_by": {
          "name": "created_by",
          "type": "text",
          "primaryKey": false,
          "notNull": true
        },
        "created_at": {
          "name": "created_at",
          "type": "timestamp",
          "primaryKey": false,
          "notNull": true,
          "default": "now()"
        }
      },
      "indexes": {
        "invites_group_id_idx": {
          "name": "invites_group_id_idx",
          "columns": [
            {
              "expression": "group_id",
              "isExpression": false,
              "asc": true,
              "nulls": "last"
            }
          ],
          "isUnique": false,
          "concurrently": false,
          "method": "btree",
          "with": {}
        },
        "invites_token_idx": {
          "name": "invites_token_idx",
          "columns": [
            {
              "expression": "token",
              "isExpression": false,
              "asc": true,
              "nulls": "last"
            }
          ],
          "isUnique": false,
          "concurrently": false,
          "method": "btree",
          "with": {}
        }
      },
      "foreignKeys": {
        "invites_group_id_groups_id_fk": {
          "name": "invites_group_id_groups_id_fk",
          "tableFrom": "invites",
          "tableTo": "groups",
          "columnsFrom": [
            "group_id"
          ],
          "columnsTo": [
            "id"
          ],
          "onDelete": "cascade",
          "onUpdate": "no action"
        },
        "invites_created_by_user_id_fk": {
          "name": "invites_created_by_user_id_fk",
          "tableFrom": "invites",
          "tableTo": "user",
          "columnsFrom": [
            "created_by"
          ],
          "columnsTo": [
            "id"
          ],
          "onDelete": "no action",
          "onUpdate": "no action"
        }
      },
      "compositePrimaryKeys": {},
      "uniqueConstraints": {
        "invites_token_unique": {
          "name": "invites_token_unique",
          "nullsNotDistinct": false,
          "columns": [
            "token"
          ]
        }
      },
      "policies": {},
      "checkConstraints": {},
      "isRLSEnabled": false
    },
    "public.members": {
      "name": "members",
      "schema": "",
      "columns": {
        "id": {
          "name": "id",
          "type": "text",
          "primaryKey": true,
          "notNull": true
        },
        "group_id": {
          "name": "group_id",
          "type": "text",
          "primaryKey": false,
          "notNull": true
        },
        "display_name": {
          "name": "display_name",
          "type": "text",
          "primaryKey": false,
          "notNull": true
        },
        "user_id": {
          "name": "user_id",
          "type": "text",
          "primaryKey": false,
          "notNull": false
        },
        "deactivated_at": {
          "name": "deactivated_at",
          "type": "timestamp",
          "primaryKey": false,
          "notNull": false
        }
      },
      "indexes": {
        "members_group_id_idx": {
          "name": "members_group_id_idx",
          "columns": [
            {
              "expression": "group_id",
              "isExpression": false,
              "asc": true,
              "nulls": "last"
            }
          ],
          "isUnique": false,
          "concurrently": false,
          "method": "btree",
          "with": {}
        },
        "members_user_id_idx": {
          "name": "members_user_id_idx",
          "columns": [
            {
              "expression": "user_id",
              "isExpression": false,
              "asc": true,
              "nulls": "last"
            }
          ],
          "isUnique": false,
          "concurrently": false,
          "method": "btree",
          "with": {}
        },
        "members_group_id_user_id_unique": {
          "name": "members_group_id_user_id_unique",
          "columns": [
            {
              "expression": "group_id",
              "isExpression": false,
              "asc": true,
              "nulls": "last"
            },
            {
              "expression": "user_id",
              "isExpression": false,
              "asc": true,
              "nulls": "last"
            }
          ],
          "isUnique": true,
          "where": "\"members\".\"user_id\" is not null",
          "concurrently": false,
          "method": "btree",
          "with": {}
        }
      },
      "foreignKeys": {
        "members_group_id_groups_id_fk": {
          "name": "members_group_id_groups_id_fk",
          "tableFrom": "members",
          "tableTo": "groups",
          "columnsFrom": [
            "group_id"
          ],
          "columnsTo": [
            "id"
          ],
          "onDelete": "cascade",
          "onUpdate": "no action"
        },
        "members_user_id_user_id_fk": {
          "name": "members_user_id_user_id_fk",
          "tableFrom": "members",
          "tableTo": "user",
          "columnsFrom": [
            "user_id"
          ],
          "columnsTo": [
            "id"
          ],
          "onDelete": "set null",
          "onUpdate": "no action"
        }
      },
      "compositePrimaryKeys": {},
      "uniqueConstraints": {},
      "policies": {},
      "checkConstraints": {},
      "isRLSEnabled": false
    },
    "public.currencies": {
      "name": "currencies",
      "schema": "",
      "columns": {
        "code": {
          "name": "code",
          "type": "text",
          "primaryKey": true,
          "notNull": true
        },
        "name": {
          "name": "name",
          "type": "text",
          "primaryKey": false,
          "notNull": true
        },
        "exponent": {
          "name": "exponent",
          "type": "integer",
          "primaryKey": false,
          "notNull": true
        },
        "symbol": {
          "name": "symbol",
          "type": "text",
          "primaryKey": false,
          "notNull": true
        }
      },
      "indexes": {},
      "foreignKeys": {},
      "compositePrimaryKeys": {},
      "uniqueConstraints": {},
      "policies": {},
      "checkConstraints": {},
      "isRLSEnabled": false
    },
    "public.categories": {
      "name": "categories",
      "schema": "",
      "columns": {
        "id": {
          "name": "id",
          "type": "text",
          "primaryKey": true,
          "notNull": true
        },
        "name": {
          "name": "name",
          "type": "text",
          "primaryKey": false,
          "notNull": true
        },
        "icon": {
          "name": "icon",
          "type": "text",
          "primaryKey": false,
          "notNull": true
        },
        "applies_to": {
          "name": "applies_to",
          "type": "text",
          "primaryKey": false,
          "notNull": true
        },
        "sort_order": {
          "name": "sort_order",
          "type": "integer",
          "primaryKey": false,
          "notNull": true
        }
      },
      "indexes": {},
      "foreignKeys": {},
      "compositePrimaryKeys": {},
      "uniqueConstraints": {},
      "policies": {},
      "checkConstraints": {},
      "isRLSEnabled": false
    },
    "public.transaction_charges": {
      "name": "transaction_charges",
      "schema": "",
      "columns": {
        "id": {
          "name": "id",
          "type": "text",
          "primaryKey": true,
          "notNull": true
        },
        "transaction_id": {
          "name": "transaction_id",
          "type": "text",
          "primaryKey": false,
          "notNull": true
        },
        "kind": {
          "name": "kind",
          "type": "text",
          "primaryKey": false,
          "notNull": true
        },
        "mode": {
          "name": "mode",
          "type": "text",
          "primaryKey": false,
          "notNull": true
        },
        "value": {
          "name": "value",
          "type": "bigint",
          "primaryKey": false,
          "notNull": true
        },
        "base": {
          "name": "base",
          "type": "text",
          "primaryKey": false,
          "notNull": true
        },
        "sort_order": {
          "name": "sort_order",
          "type": "integer",
          "primaryKey": false,
          "notNull": true
        }
      },
      "indexes": {
        "transaction_charges_transaction_id_idx": {
          "name": "transaction_charges_transaction_id_idx",
          "columns": [
            {
              "expression": "transaction_id",
              "isExpression": false,
              "asc": true,
              "nulls": "last"
            }
          ],
          "isUnique": false,
          "concurrently": false,
          "method": "btree",
          "with": {}
        }
      },
      "foreignKeys": {
        "transaction_charges_transaction_id_transactions_id_fk": {
          "name": "transaction_charges_transaction_id_transactions_id_fk",
          "tableFrom": "transaction_charges",
          "tableTo": "transactions",
          "columnsFrom": [
            "transaction_id"
          ],
          "columnsTo": [
            "id"
          ],
          "onDelete": "cascade",
          "onUpdate": "no action"
        }
      },
      "compositePrimaryKeys": {},
      "uniqueConstraints": {},
      "policies": {},
      "checkConstraints": {},
      "isRLSEnabled": false
    },
    "public.transaction_item_shares": {
      "name": "transaction_item_shares",
      "schema": "",
      "columns": {
        "item_id": {
          "name": "item_id",
          "type": "text",
          "primaryKey": false,
          "notNull": true
        },
        "member_id": {
          "name": "member_id",
          "type": "text",
          "primaryKey": false,
          "notNull": true
        },
        "amount_owed": {
          "name": "amount_owed",
          "type": "bigint",
          "primaryKey": false,
          "notNull": true
        },
        "split_mode": {
          "name": "split_mode",
          "type": "text",
          "primaryKey": false,
          "notNull": true
        },
        "share_weight": {
          "name": "share_weight",
          "type": "integer",
          "primaryKey": false,
          "notNull": false
        },
        "raw_amount": {
          "name": "raw_amount",
          "type": "bigint",
          "primaryKey": false,
          "notNull": false
        }
      },
      "indexes": {
        "transaction_item_shares_item_id_idx": {
          "name": "transaction_item_shares_item_id_idx",
          "columns": [
            {
              "expression": "item_id",
              "isExpression": false,
              "asc": true,
              "nulls": "last"
            }
          ],
          "isUnique": false,
          "concurrently": false,
          "method": "btree",
          "with": {}
        }
      },
      "foreignKeys": {
        "transaction_item_shares_item_id_transaction_items_id_fk": {
          "name": "transaction_item_shares_item_id_transaction_items_id_fk",
          "tableFrom": "transaction_item_shares",
          "tableTo": "transaction_items",
          "columnsFrom": [
            "item_id"
          ],
          "columnsTo": [
            "id"
          ],
          "onDelete": "cascade",
          "onUpdate": "no action"
        },
        "transaction_item_shares_member_id_members_id_fk": {
          "name": "transaction_item_shares_member_id_members_id_fk",
          "tableFrom": "transaction_item_shares",
          "tableTo": "members",
          "columnsFrom": [
            "member_id"
          ],
          "columnsTo": [
            "id"
          ],
          "onDelete": "cascade",
          "onUpdate": "no action"
        }
      },
      "compositePrimaryKeys": {
        "transaction_item_shares_item_id_member_id_pk": {
          "name": "transaction_item_shares_item_id_member_id_pk",
          "columns": [
            "item_id",
            "member_id"
          ]
        }
      },
      "uniqueConstraints": {},
      "policies": {},
      "checkConstraints": {},
      "isRLSEnabled": false
    },
    "public.transaction_items": {
      "name": "transaction_items",
      "schema": "",
      "columns": {
        "id": {
          "name": "id",
          "type": "text",
          "primaryKey": true,
          "notNull": true
        },
        "transaction_id": {
          "name": "transaction_id",
          "type": "text",
          "primaryKey": false,
          "notNull": true
        },
        "label": {
          "name": "label",
          "type": "text",
          "primaryKey": false,
          "notNull": true
        },
        "amount": {
          "name": "amount",
          "type": "bigint",
          "primaryKey": false,
          "notNull": true
        },
        "sort_order": {
          "name": "sort_order",
          "type": "integer",
          "primaryKey": false,
          "notNull": true
        }
      },
      "indexes": {
        "transaction_items_transaction_id_idx": {
          "name": "transaction_items_transaction_id_idx",
          "columns": [
            {
              "expression": "transaction_id",
              "isExpression": false,
              "asc": true,
              "nulls": "last"
            }
          ],
          "isUnique": false,
          "concurrently": false,
          "method": "btree",
          "with": {}
        }
      },
      "foreignKeys": {
        "transaction_items_transaction_id_transactions_id_fk": {
          "name": "transaction_items_transaction_id_transactions_id_fk",
          "tableFrom": "transaction_items",
          "tableTo": "transactions",
          "columnsFrom": [
            "transaction_id"
          ],
          "columnsTo": [
            "id"
          ],
          "onDelete": "cascade",
          "onUpdate": "no action"
        }
      },
      "compositePrimaryKeys": {},
      "uniqueConstraints": {},
      "policies": {},
      "checkConstraints": {},
      "isRLSEnabled": false
    },
    "public.transaction_payers": {
      "name": "transaction_payers",
      "schema": "",
      "columns": {
        "transaction_id": {
          "name": "transaction_id",
          "type": "text",
          "primaryKey": false,
          "notNull": true
        },
        "member_id": {
          "name": "member_id",
          "type": "text",
          "primaryKey": false,
          "notNull": true
        },
        "amount_paid": {
          "name": "amount_paid",
          "type": "bigint",
          "primaryKey": false,
          "notNull": true
        },
        "amount_paid_settlement": {
          "name": "amount_paid_settlement",
          "type": "bigint",
          "primaryKey": false,
          "notNull": true
        }
      },
      "indexes": {
        "transaction_payers_transaction_id_idx": {
          "name": "transaction_payers_transaction_id_idx",
          "columns": [
            {
              "expression": "transaction_id",
              "isExpression": false,
              "asc": true,
              "nulls": "last"
            }
          ],
          "isUnique": false,
          "concurrently": false,
          "method": "btree",
          "with": {}
        }
      },
      "foreignKeys": {
        "transaction_payers_transaction_id_transactions_id_fk": {
          "name": "transaction_payers_transaction_id_transactions_id_fk",
          "tableFrom": "transaction_payers",
          "tableTo": "transactions",
          "columnsFrom": [
            "transaction_id"
          ],
          "columnsTo": [
            "id"
          ],
          "onDelete": "cascade",
          "onUpdate": "no action"
        },
        "transaction_payers_member_id_members_id_fk": {
          "name": "transaction_payers_member_id_members_id_fk",
          "tableFrom": "transaction_payers",
          "tableTo": "members",
          "columnsFrom": [
            "member_id"
          ],
          "columnsTo": [
            "id"
          ],
          "onDelete": "cascade",
          "onUpdate": "no action"
        }
      },
      "compositePrimaryKeys": {
        "transaction_payers_transaction_id_member_id_pk": {
          "name": "transaction_payers_transaction_id_member_id_pk",
          "columns": [
            "transaction_id",
            "member_id"
          ]
        }
      },
      "uniqueConstraints": {},
      "policies": {},
      "checkConstraints": {},
      "isRLSEnabled": false
    },
    "public.transaction_shares": {
      "name": "transaction_shares",
      "schema": "",
      "columns": {
        "transaction_id": {
          "name": "transaction_id",
          "type": "text",
          "primaryKey": false,
          "notNull": true
        },
        "member_id": {
          "name": "member_id",
          "type": "text",
          "primaryKey": false,
          "notNull": true
        },
        "amount_owed": {
          "name": "amount_owed",
          "type": "bigint",
          "primaryKey": false,
          "notNull": true
        },
        "share_weight": {
          "name": "share_weight",
          "type": "integer",
          "primaryKey": false,
          "notNull": false
        },
        "raw_amount": {
          "name": "raw_amount",
          "type": "bigint",
          "primaryKey": false,
          "notNull": false
        }
      },
      "indexes": {
        "transaction_shares_transaction_id_idx": {
          "name": "transaction_shares_transaction_id_idx",
          "columns": [
            {
              "expression": "transaction_id",
              "isExpression": false,
              "asc": true,
              "nulls": "last"
            }
          ],
          "isUnique": false,
          "concurrently": false,
          "method": "btree",
          "with": {}
        }
      },
      "foreignKeys": {
        "transaction_shares_transaction_id_transactions_id_fk": {
          "name": "transaction_shares_transaction_id_transactions_id_fk",
          "tableFrom": "transaction_shares",
          "tableTo": "transactions",
          "columnsFrom": [
            "transaction_id"
          ],
          "columnsTo": [
            "id"
          ],
          "onDelete": "cascade",
          "onUpdate": "no action"
        },
        "transaction_shares_member_id_members_id_fk": {
          "name": "transaction_shares_member_id_members_id_fk",
          "tableFrom": "transaction_shares",
          "tableTo": "members",
          "columnsFrom": [
            "member_id"
          ],
          "columnsTo": [
            "id"
          ],
          "onDelete": "cascade",
          "onUpdate": "no action"
        }
      },
      "compositePrimaryKeys": {
        "transaction_shares_transaction_id_member_id_pk": {
          "name": "transaction_shares_transaction_id_member_id_pk",
          "columns": [
            "transaction_id",
            "member_id"
          ]
        }
      },
      "uniqueConstraints": {},
      "policies": {},
      "checkConstraints": {},
      "isRLSEnabled": false
    },
    "public.transactions": {
      "name": "transactions",
      "schema": "",
      "columns": {
        "id": {
          "name": "id",
          "type": "text",
          "primaryKey": true,
          "notNull": true
        },
        "group_id": {
          "name": "group_id",
          "type": "text",
          "primaryKey": false,
          "notNull": true
        },
        "type": {
          "name": "type",
          "type": "text",
          "primaryKey": false,
          "notNull": true
        },
        "title": {
          "name": "title",
          "type": "text",
          "primaryKey": false,
          "notNull": true
        },
        "category_id": {
          "name": "category_id",
          "type": "text",
          "primaryKey": false,
          "notNull": true
        },
        "amount_total": {
          "name": "amount_total",
          "type": "bigint",
          "primaryKey": false,
          "notNull": true
        },
        "currency": {
          "name": "currency",
          "type": "text",
          "primaryKey": false,
          "notNull": true
        },
        "exchange_rate": {
          "name": "exchange_rate",
          "type": "numeric(18, 6)",
          "primaryKey": false,
          "notNull": true
        },
        "amount_total_settlement": {
          "name": "amount_total_settlement",
          "type": "bigint",
          "primaryKey": false,
          "notNull": true
        },
        "split_mode": {
          "name": "split_mode",
          "type": "text",
          "primaryKey": false,
          "notNull": true
        },
        "created_by": {
          "name": "created_by",
          "type": "text",
          "primaryKey": false,
          "notNull": true
        },
        "occurred_at": {
          "name": "occurred_at",
          "type": "timestamp (3)",
          "primaryKey": false,
          "notNull": true,
          "default": "now()"
        },
        "created_at": {
          "name": "created_at",
          "type": "timestamp (3)",
          "primaryKey": false,
          "notNull": true,
          "default": "now()"
        },
        "updated_at": {
          "name": "updated_at",
          "type": "timestamp",
          "primaryKey": false,
          "notNull": true,
          "default": "now()"
        },
        "deleted_at": {
          "name": "deleted_at",
          "type": "timestamp",
          "primaryKey": false,
          "notNull": false
        }
      },
      "indexes": {
        "transactions_group_id_occurred_at_idx": {
          "name": "transactions_group_id_occurred_at_idx",
          "columns": [
            {
              "expression": "group_id",
              "isExpression": false,
              "asc": true,
              "nulls": "last"
            },
            {
              "expression": "occurred_at",
              "isExpression": false,
              "asc": true,
              "nulls": "last"
            }
          ],
          "isUnique": false,
          "concurrently": false,
          "method": "btree",
          "with": {}
        },
        "transactions_group_id_created_at_idx": {
          "name": "transactions_group_id_created_at_idx",
          "columns": [
            {
              "expression": "group_id",
              "isExpression": false,
              "asc": true,
              "nulls": "last"
            },
            {
              "expression": "created_at",
              "isExpression": false,
              "asc": false,
              "nulls": "last"
            },
            {
              "expression": "occurred_at",
              "isExpression": false,
              "asc": false,
              "nulls": "last"
            }
          ],
          "isUnique": false,
          "concurrently": false,
          "method": "btree",
          "with": {}
        }
      },
      "foreignKeys": {
        "transactions_group_id_groups_id_fk": {
          "name": "transactions_group_id_groups_id_fk",
          "tableFrom": "transactions",
          "tableTo": "groups",
          "columnsFrom": [
            "group_id"
          ],
          "columnsTo": [
            "id"
          ],
          "onDelete": "cascade",
          "onUpdate": "no action"
        },
        "transactions_category_id_categories_id_fk": {
          "name": "transactions_category_id_categories_id_fk",
          "tableFrom": "transactions",
          "tableTo": "categories",
          "columnsFrom": [
            "category_id"
          ],
          "columnsTo": [
            "id"
          ],
          "onDelete": "no action",
          "onUpdate": "no action"
        },
        "transactions_currency_currencies_code_fk": {
          "name": "transactions_currency_currencies_code_fk",
          "tableFrom": "transactions",
          "tableTo": "currencies",
          "columnsFrom": [
            "currency"
          ],
          "columnsTo": [
            "code"
          ],
          "onDelete": "no action",
          "onUpdate": "no action"
        },
        "transactions_created_by_user_id_fk": {
          "name": "transactions_created_by_user_id_fk",
          "tableFrom": "transactions",
          "tableTo": "user",
          "columnsFrom": [
            "created_by"
          ],
          "columnsTo": [
            "id"
          ],
          "onDelete": "no action",
          "onUpdate": "no action"
        }
      },
      "compositePrimaryKeys": {},
      "uniqueConstraints": {},
      "policies": {},
      "checkConstraints": {},
      "isRLSEnabled": false
    },
    "public.audit_log": {
      "name": "audit_log",
      "schema": "",
      "columns": {
        "id": {
          "name": "id",
          "type": "text",
          "primaryKey": true,
          "notNull": true
        },
        "group_id": {
          "name": "group_id",
          "type": "text",
          "primaryKey": false,
          "notNull": true
        },
        "actor_user_id": {
          "name": "actor_user_id",
          "type": "text",
          "primaryKey": false,
          "notNull": true
        },
        "action": {
          "name": "action",
          "type": "text",
          "primaryKey": false,
          "notNull": true
        },
        "entity_type": {
          "name": "entity_type",
          "type": "text",
          "primaryKey": false,
          "notNull": true
        },
        "entity_id": {
          "name": "entity_id",
          "type": "text",
          "primaryKey": false,
          "notNull": true
        },
        "summary": {
          "name": "summary",
          "type": "text",
          "primaryKey": false,
          "notNull": true
        },
        "metadata": {
          "name": "metadata",
          "type": "jsonb",
          "primaryKey": false,
          "notNull": false
        },
        "occurred_at": {
          "name": "occurred_at",
          "type": "timestamp",
          "primaryKey": false,
          "notNull": true,
          "default": "now()"
        }
      },
      "indexes": {
        "audit_log_group_id_occurred_at_idx": {
          "name": "audit_log_group_id_occurred_at_idx",
          "columns": [
            {
              "expression": "group_id",
              "isExpression": false,
              "asc": true,
              "nulls": "last"
            },
            {
              "expression": "occurred_at",
              "isExpression": false,
              "asc": false,
              "nulls": "last"
            }
          ],
          "isUnique": false,
          "concurrently": false,
          "method": "btree",
          "with": {}
        },
        "audit_log_entity_type_entity_id_idx": {
          "name": "audit_log_entity_type_entity_id_idx",
          "columns": [
            {
              "expression": "entity_type",
              "isExpression": false,
              "asc": true,
              "nulls": "last"
            },
            {
              "expression": "entity_id",
              "isExpression": false,
              "asc": true,
              "nulls": "last"
            }
          ],
          "isUnique": false,
          "concurrently": false,
          "method": "btree",
          "with": {}
        }
      },
      "foreignKeys": {
        "audit_log_group_id_groups_id_fk": {
          "name": "audit_log_group_id_groups_id_fk",
          "tableFrom": "audit_log",
          "tableTo": "groups",
          "columnsFrom": [
            "group_id"
          ],
          "columnsTo": [
            "id"
          ],
          "onDelete": "cascade",
          "onUpdate": "no action"
        },
        "audit_log_actor_user_id_user_id_fk": {
          "name": "audit_log_actor_user_id_user_id_fk",
          "tableFrom": "audit_log",
          "tableTo": "user",
          "columnsFrom": [
            "actor_user_id"
          ],
          "columnsTo": [
            "id"
          ],
          "onDelete": "no action",
          "onUpdate": "no action"
        }
      },
      "compositePrimaryKeys": {},
      "uniqueConstraints": {},
      "policies": {},
      "checkConstraints": {},
      "isRLSEnabled": false
    },
    "public.idempotency_key": {
      "name": "idempotency_key",
      "schema": "",
      "columns": {
        "id": {
          "name": "id",
          "type": "text",
          "primaryKey": true,
          "notNull": true
        },
        "key_id": {
          "name": "key_id",
          "type": "text",
          "primaryKey": false,
          "notNull": true
        },
        "idempotency_key": {
          "name": "idempotency_key",
          "type": "text",
          "primaryKey": false,
          "notNull": true
        },
        "request_hash": {
          "name": "request_hash",
          "type": "text",
          "primaryKey": false,
          "notNull": true
        },
        "status": {
          "name": "status",
          "type": "text",
          "primaryKey": false,
          "notNull": true,
          "default": "'pending'"
        },
        "response_status": {
          "name": "response_status",
          "type": "integer",
          "primaryKey": false,
          "notNull": false
        },
        "response_body": {
          "name": "response_body",
          "type": "jsonb",
          "primaryKey": false,
          "notNull": false
        },
        "created_at": {
          "name": "created_at",
          "type": "timestamp",
          "primaryKey": false,
          "notNull": true,
          "default": "now()"
        },
        "expires_at": {
          "name": "expires_at",
          "type": "timestamp",
          "primaryKey": false,
          "notNull": true
        }
      },
      "indexes": {},
      "foreignKeys": {
        "idempotency_key_key_id_api_key_id_fk": {
          "name": "idempotency_key_key_id_api_key_id_fk",
          "tableFrom": "idempotency_key",
          "tableTo": "api_key",
          "columnsFrom": [
            "key_id"
          ],
          "columnsTo": [
            "id"
          ],
          "onDelete": "cascade",
          "onUpdate": "no action"
        }
      },
      "compositePrimaryKeys": {},
      "uniqueConstraints": {
        "idempotency_key_key_id_key_unq": {
          "name": "idempotency_key_key_id_key_unq",
          "nullsNotDistinct": false,
          "columns": [
            "key_id",
            "idempotency_key"
          ]
        }
      },
      "policies": {},
      "checkConstraints": {},
      "isRLSEnabled": false
    }
  },
  "enums": {},
  "schemas": {},
  "sequences": {},
  "roles": {},
  "policies": {},
  "views": {},
  "_meta": {
    "columns": {},
    "schemas": {},
    "tables": {}
  }
}